PyVersionNumber
